lazyslurm/__init__.py
lazyslurm/config.py
lazyslurm/main.py
lazyslurm/process_ui.py
lazyslurm/test.py
lazyslurm/utils.py
lazyslurm/process/__init__.py
lazyslurm/process/commands.py
lazyslurm/slurm/__init__.py
lazyslurm/slurm/commands.py
lazyslurm/slurm/parser.py
lazyslurm/ui/__init__.py
lazyslurm/ui/palettes.py
lazyslurm/ui/popups.py
lazyslurm/ui/screens.py
lazyslurm/ui/tab_widgets.py
lazyslurm/ui/widgets.py
lazyslurm-0.1.0.dist-info/licenses/LICENSE
tests/__init__.py
tests/test_commands.py
tests/test_confirmation_handlers.py
tests/test_confirmation_popup.py
tests/test_parser.py
tests/test_screens.py
lazyslurm-0.1.0.dist-info/METADATA
lazyslurm-0.1.0.dist-info/WHEEL
lazyslurm-0.1.0.dist-info/entry_points.txt
lazyslurm-0.1.0.dist-info/top_level.txt
lazyslurm-0.1.0.dist-info/RECORD
