Metadata-Version: 2.4
Name: lazyslurm
Version: 0.1.0
Summary: A interface for SLURM job management.
Home-page: https://github.com/mtsodf/lazyslurm
Author: Mateus Figueiredo
Author-email: mtsodf@gmail.com
Classifier: Programming Language :: Python :: 3
Classifier: License :: OSI Approved :: MIT License
Classifier: Operating System :: OS Independent
Requires-Python: >=3.9
License-File: LICENSE
Requires-Dist: urwid
Requires-Dist: plumbum
Dynamic: author
Dynamic: author-email
Dynamic: classifier
Dynamic: description
Dynamic: description-content-type
Dynamic: home-page
Dynamic: license-file
Dynamic: requires-dist
Dynamic: requires-python
Dynamic: summary
